elvia_louvre/__init__.py
elvia_louvre/config.py
elvia_louvre/data_models.py
elvia_louvre/enums.py
elvia_louvre/errors.py
elvia_louvre/image_api.py
elvia_louvre/image_enhance_api.py
elvia_louvre/louvre_client.py
elvia_louvre/token.py
elvia_louvre-0.3.3.dist-info/METADATA
elvia_louvre-0.3.3.dist-info/WHEEL
elvia_louvre-0.3.3.dist-info/top_level.txt
elvia_louvre-0.3.3.dist-info/RECORD
