Metadata-Version: 2.1
Name: elvia-louvre
Version: 0.3.3
Summary: elvia-louvre Python package
Author: Elvia
Requires-Dist: elvia-vault (>=0.3.1)
Requires-Dist: pillow (>=9.3.0)
